{
  "openapi": "3.0.4",
  "info": {
    "title": "KeellsBackend",
    "version": "1.0"
  },
  "paths": {
    "/api/Department": {
      "get": {
        "tags": [
          "Department"
        ],
        "responses": {
          "200": {
            "description": "OK"
          }
        }
      },
      "post": {
        "tags": [
          "Department"
        ],
        "requestBody": {
          "content": {
            "application/json": {
              "schema": {
                "$ref": "#/components/schemas/DepartmentCreateDto"
              }
            },
            "text/json": {
              "schema": {
                "$ref": "#/components/schemas/DepartmentCreateDto"
              }
            },
            "application/*+json": {
              "schema": {
                "$ref": "#/components/schemas/DepartmentCreateDto"
              }
            }
          }
        },
        "responses": {
          "200": {
            "description": "OK"
          }
        }
      },
      "put": {
        "tags": [
          "Department"
        ],
        "requestBody": {
          "content": {
            "application/json": {
              "schema": {
                "$ref": "#/components/schemas/DepartmentUpdateDto"
              }
            },
            "text/json": {
              "schema": {
                "$ref": "#/components/schemas/DepartmentUpdateDto"
              }
            },
            "application/*+json": {
              "schema": {
                "$ref": "#/components/schemas/DepartmentUpdateDto"
              }
            }
          }
        },
        "responses": {
          "200": {
            "description": "OK"
          }
        }
      }
    },
    "/api/Department/{id}": {
      "get": {
        "tags": [
          "Department"
        ],
        "parameters": [
          {
            "name": "id",
            "in": "path",
            "required": true,
            "schema": {
              "type": "integer",
              "format": "int32"
            }
          }
        ],
        "responses": {
          "200": {
            "description": "OK"
          }
        }
      },
      "delete": {
        "tags": [
          "Department"
        ],
        "parameters": [
          {
            "name": "id",
            "in": "path",
            "required": true,
            "schema": {
              "type": "integer",
              "format": "int32"
            }
          }
        ],
        "responses": {
          "200": {
            "description": "OK"
          }
        }
      }
    },
    "/api/Department/reactivate/{id}": {
      "post": {
        "tags": [
          "Department"
        ],
        "parameters": [
          {
            "name": "id",
            "in": "path",
            "required": true,
            "schema": {
              "type": "integer",
              "format": "int32"
            }
          }
        ],
        "requestBody": {
          "content": {
            "application/json": {
              "schema": {
                "$ref": "#/components/schemas/DepartmentCreateDto"
              }
            },
            "text/json": {
              "schema": {
                "$ref": "#/components/schemas/DepartmentCreateDto"
              }
            },
            "application/*+json": {
              "schema": {
                "$ref": "#/components/schemas/DepartmentCreateDto"
              }
            }
          }
        },
        "responses": {
          "200": {
            "description": "OK"
          }
        }
      }
    },
    "/api/Employee": {
      "get": {
        "tags": [
          "Employee"
        ],
        "responses": {
          "200": {
            "description": "OK"
          }
        }
      },
      "post": {
        "tags": [
          "Employee"
        ],
        "requestBody": {
          "content": {
            "application/json": {
              "schema": {
                "$ref": "#/components/schemas/EmployeeCreateDto"
              }
            },
            "text/json": {
              "schema": {
                "$ref": "#/components/schemas/EmployeeCreateDto"
              }
            },
            "application/*+json": {
              "schema": {
                "$ref": "#/components/schemas/EmployeeCreateDto"
              }
            }
          }
        },
        "responses": {
          "200": {
            "description": "OK"
          }
        }
      },
      "put": {
        "tags": [
          "Employee"
        ],
        "requestBody": {
          "content": {
            "application/json": {
              "schema": {
                "$ref": "#/components/schemas/EmployeeUpdateDto"
              }
            },
            "text/json": {
              "schema": {
                "$ref": "#/components/schemas/EmployeeUpdateDto"
              }
            },
            "application/*+json": {
              "schema": {
                "$ref": "#/components/schemas/EmployeeUpdateDto"
              }
            }
          }
        },
        "responses": {
          "200": {
            "description": "OK"
          }
        }
      }
    },
    "/api/Employee/{id}": {
      "get": {
        "tags": [
          "Employee"
        ],
        "parameters": [
          {
            "name": "id",
            "in": "path",
            "required": true,
            "schema": {
              "type": "integer",
              "format": "int32"
            }
          }
        ],
        "responses": {
          "200": {
            "description": "OK"
          }
        }
      },
      "delete": {
        "tags": [
          "Employee"
        ],
        "parameters": [
          {
            "name": "id",
            "in": "path",
            "required": true,
            "schema": {
              "type": "integer",
              "format": "int32"
            }
          }
        ],
        "responses": {
          "200": {
            "description": "OK"
          }
        }
      }
    },
    "/WeatherForecast": {
      "get": {
        "tags": [
          "WeatherForecast"
        ],
        "operationId": "GetWeatherForecast",
        "responses": {
          "200": {
            "description": "OK",
            "content": {
              "text/plain": {
                "schema": {
                  "type": "array",
                  "items": {
                    "$ref": "#/components/schemas/WeatherForecast"
                  }
                }
              },
              "application/json": {
                "schema": {
                  "type": "array",
                  "items": {
                    "$ref": "#/components/schemas/WeatherForecast"
                  }
                }
              },
              "text/json": {
                "schema": {
                  "type": "array",
                  "items": {
                    "$ref": "#/components/schemas/WeatherForecast"
                  }
                }
              }
            }
          }
        }
      }
    }
  },
  "components": {
    "schemas": {
      "DepartmentCreateDto": {
        "type": "object",
        "properties": {
          "departmentCode": {
            "type": "string",
            "nullable": true
          },
          "departmentName": {
            "type": "string",
            "nullable": true
          },
          "createdAt": {
            "type": "string",
            "format": "date-time"
          },
          "modifiedAt": {
            "type": "string",
            "format": "date-time",
            "nullable": true
          }
        },
        "additionalProperties": false
      },
      "DepartmentUpdateDto": {
        "type": "object",
        "properties": {
          "departmentId": {
            "type": "integer",
            "format": "int32"
          },
          "departmentCode": {
            "type": "string",
            "nullable": true
          },
          "departmentName": {
            "type": "string",
            "nullable": true
          },
          "createdAt": {
            "type": "string",
            "format": "date-time"
          },
          "modifiedAt": {
            "type": "string",
            "format": "date-time",
            "nullable": true
          }
        },
        "additionalProperties": false
      },
      "EmployeeCreateDto": {
        "type": "object",
        "properties": {
          "firstName": {
            "type": "string",
            "nullable": true
          },
          "lastName": {
            "type": "string",
            "nullable": true
          },
          "email": {
            "type": "string",
            "nullable": true
          },
          "dateOfBirth": {
            "type": "string",
            "format": "date-time"
          },
          "salary": {
            "type": "number",
            "format": "double"
          },
          "departmentId": {
            "type": "integer",
            "format": "int32"
          },
          "createdAt": {
            "type": "string",
            "format": "date-time"
          },
          "modifiedAt": {
            "type": "string",
            "format": "date-time",
            "nullable": true
          }
        },
        "additionalProperties": false
      },
      "EmployeeUpdateDto": {
        "type": "object",
        "properties": {
          "employeeId": {
            "type": "integer",
            "format": "int32"
          },
          "firstName": {
            "type": "string",
            "nullable": true
          },
          "lastName": {
            "type": "string",
            "nullable": true
          },
          "email": {
            "type": "string",
            "nullable": true
          },
          "dateOfBirth": {
            "type": "string",
            "format": "date-time"
          },
          "salary": {
            "type": "number",
            "format": "double"
          },
          "departmentId": {
            "type": "integer",
            "format": "int32"
          },
          "createdAt": {
            "type": "string",
            "format": "date-time"
          },
          "modifiedAt": {
            "type": "string",
            "format": "date-time",
            "nullable": true
          }
        },
        "additionalProperties": false
      },
      "WeatherForecast": {
        "type": "object",
        "properties": {
          "date": {
            "type": "string",
            "format": "date"
          },
          "temperatureC": {
            "type": "integer",
            "format": "int32"
          },
          "temperatureF": {
            "type": "integer",
            "format": "int32",
            "readOnly": true
          },
          "summary": {
            "type": "string",
            "nullable": true
          }
        },
        "additionalProperties": false
      }
    }
  },
  "tags": [
    {
      "name": "Department"
    },
    {
      "name": "Employee"
    },
    {
      "name": "WeatherForecast"
    }
  ]
}